nextchat/__init__.py
nextchat/bot.py
nextchat/context.py
nextchat/help.py
nextchat/message.py
nextchat-1.0.0.2.dist-info/WHEEL
nextchat-1.0.0.2.dist-info/METADATA
nextchat-1.0.0.2.dist-info/RECORD
